{
  "props": {
    "shadowBox": false,
    "width": "full",
    "margin": false,
    "grid": false,
    "background": "primary1"
  },
  "items": [
    {
      "type": "header",
      "order": 0,
      "props": {
        "label": "Vi hjälper dig hela vägen",
        "strength": 2,
        "align": "center"
      }
    },
    {
      "type": "cta-element",
      "order": "1",
      "props": {
        "label": "Bli medlem"
      }
    },
    {
      "type": "paragraf",
      "order": "2",
      "props": {
        "text": ""
      }
    }
  ]
}
